riboswitchinator/__init__.py
riboswitchinator/executable.py
riboswitchinator-0.0.2.dist-info/LICENSE
riboswitchinator-0.0.2.dist-info/WHEEL
riboswitchinator-0.0.2.dist-info/entry_points.txt
riboswitchinator-0.0.2.dist-info/METADATA
riboswitchinator-0.0.2.dist-info/RECORD
